flaskignoressl/__init__.py
flaskignoressl/module.py
ignoressl/__init__.py
ignoressl/module.py
flaskignoressl-0.0.2.dist-info/METADATA
flaskignoressl-0.0.2.dist-info/WHEEL
flaskignoressl-0.0.2.dist-info/top_level.txt
flaskignoressl-0.0.2.dist-info/RECORD
