Metadata-Version: 2.1
Name: flaskignoressl
Version: 0.0.2
Requires-Dist: requests
